emailify/__init__.py
emailify/models.py
emailify/renderers/__init__.py
emailify/renderers/api.py
emailify/renderers/core.py
emailify/renderers/fill.py
emailify/renderers/image.py
emailify/renderers/link.py
emailify/renderers/render.py
emailify/renderers/render_mjml.py
emailify/renderers/style.py
emailify/renderers/table.py
emailify/renderers/text.py
emailify/resources/__init__.py
emailify/resources/mjml.json
emailify/resources/styles.json
emailify/resources/js/call_mjml.js
emailify/resources/js/capture_export.js
emailify/resources/js/mjml-browser.js
emailify/resources/js/setup_shim.js
emailify/resources/templates/__init__.py
emailify/resources/templates/fill.mjml
emailify/resources/templates/image.mjml
emailify/resources/templates/index.mjml
emailify/resources/templates/link.mjml
emailify/resources/templates/table.mjml
emailify/resources/templates/text.mjml
emailify/styles/__init__.py
emailify/styles/image_default.py
emailify/styles/table_default.py
emailify-0.1.14.dist-info/METADATA
emailify-0.1.14.dist-info/WHEEL
emailify-0.1.14.dist-info/top_level.txt
emailify-0.1.14.dist-info/RECORD
