Metadata-Version: 2.4
Name: emailify
Version: 0.1.14
Summary: Emailify is a library for creating email templates in Python.
Requires-Python: <3.13,>=3.9.10
Requires-Dist: jinja2>=3.1.6
Requires-Dist: pandas>=2.3.1
Requires-Dist: pillow>=11.3.0
Requires-Dist: pydantic>=2.11.7
Requires-Dist: quickjs>=1.19.4
